Metadata-Version: 2.1
Name: trainax
Version: 0.0.2
Summary: Training methodologies for Autoregressive Neural Emulators in JAX built on top of Equinox & Optax.
Author: Felix Koehler
Project-URL: repository, https://github.com/Ceyron/pdequinox
Keywords: jax,sciml,deep-learning,pde,neural operator
Requires-Python: ~=3.10
License-File: LICENSE.txt
Requires-Dist: jax >=0.4.13
Requires-Dist: jaxtyping >=0.2.20
Requires-Dist: typing-extensions >=4.5.0
Requires-Dist: equinox >=0.11.3
Requires-Dist: optax >=0.2.0
Requires-Dist: tqdm >=4.63.2
